rtl/pc.v
module pc (
    input  wire        clk,
    input  wire        reset,
    input  wire [31:0] next_pc,
    output reg  [31:0] pc
);

    always @(posedge clk) begin
        if (reset)
            pc <= 32'h00000000;
        else
            pc <= next_pc;
    end

endmodule

rtl/data_memory.v
module data_memory (
    input  wire        clk,
    input  wire        reset,
    input  wire        mem_read,
    input  wire        mem_write,
    input  wire [31:0] address,
    input  wire [31:0] write_data,
    output reg  [31:0] read_data
);

    reg [31:0] memory [0:255];
    integer i;

    always @(posedge clk) begin
        if (reset) begin
            for (i = 0; i < 256; i = i + 1)
                memory[i] <= 32'h00000000;
        end
        else if (mem_write) begin
            memory[address[9:2]] <= write_data;
        end
    end

    always @(*) begin
        if (mem_read)
            read_data = memory[address[9:2]];
        else
            read_data = 32'h00000000;
    end

endmodule

rtl/alu.v
module alu (
    input  wire [31:0] a,
    input  wire [31:0] b,
    input  wire [3:0]  alu_control,
    output reg  [31:0] result,
    output wire        zero
);

    always @(*) begin
        case (alu_control)
            4'b0000: result = a + b;  // ADD
            4'b0001: result = a - b;  // SUB
            4'b0010: result = a & b;  // AND
            4'b0011: result = a | b;  // OR
            4'b0100: result = a ^ b;  // XOR
            4'b0101: result = (a < b) ? 32'd1 : 32'd0; // SLT
            default: result = 32'h00000000;
        endcase
    end

    assign zero = (result == 32'h00000000);

endmodule

rtl/immediate_generator.v
module immediate_generator (
    input  wire [31:0] instruction,
    output reg  [31:0] immediate
);

    wire [6:0] opcode;

    assign opcode = instruction[6:0];

    always @(*) begin
        case (opcode)

            // I-type: ADDI, LW
            7'b0010011,
            7'b0000011:
                immediate = {{20{instruction[31]}}, instruction[31:20]};

            // S-type: SW
            7'b0100011:
                immediate = {{20{instruction[31]}},
                             instruction[31:25],
                             instruction[11:7]};

            // B-type: BEQ, BNE
            7'b1100011:
                immediate = {{19{instruction[31]}},
                             instruction[31],
                             instruction[7],
                             instruction[30:25],
                             instruction[11:8],
                             1'b0};

            // J-type: JAL
            7'b1101111:
                immediate = {{11{instruction[31]}},
                             instruction[31],
                             instruction[19:12],
                             instruction[20],
                             instruction[30:21],
                             1'b0};

            default:
                immediate = 32'h00000000;

        endcase
    end

endmodule

rtl/register_file.v
module register_file (
    input  wire        clk,
    input  wire        reset,
    input  wire        reg_write,
    input  wire [4:0]  rs1,
    input  wire [4:0]  rs2,
    input  wire [4:0]  rd,
    input  wire [31:0] write_data,
    output wire [31:0] read_data1,
    output wire [31:0] read_data2
);

    reg [31:0] registers [0:31];
    integer i;

    always @(posedge clk) begin
        if (reset) begin
            for (i = 0; i < 32; i = i + 1)
                registers[i] <= 32'h00000000;
        end
        else if (reg_write && (rd != 5'd0)) begin
            registers[rd] <= write_data;
        end
    end

    assign read_data1 = (rs1 == 5'd0) ? 32'h00000000 : registers[rs1];
    assign read_data2 = (rs2 == 5'd0) ? 32'h00000000 : registers[rs2];

endmodule

rtl/control_unit.v
module control_unit (
    input  wire [6:0] opcode,
    input  wire [2:0] funct3,

    output reg        reg_write,
    output reg        mem_read,
    output reg        mem_write,
    output reg        alu_src,
    output reg        mem_to_reg,
    output reg        branch,
    output reg        jump,
    output reg [1:0]  branch_type,
    output reg [1:0]  alu_op
);

    always @(*) begin

        // Default control signals
        reg_write   = 1'b0;
        mem_read    = 1'b0;
        mem_write   = 1'b0;
        alu_src     = 1'b0;
        mem_to_reg  = 1'b0;
        branch      = 1'b0;
        jump        = 1'b0;
        branch_type = 2'b00;
        alu_op      = 2'b00;

        case (opcode)

            // R-type: ADD, SUB, AND, OR, XOR
            7'b0110011: begin
                reg_write = 1'b1;
                alu_src   = 1'b0;
                alu_op    = 2'b10;
            end

            // I-type: ADDI
            7'b0010011: begin
                reg_write = 1'b1;
                alu_src   = 1'b1;
                alu_op    = 2'b11;
            end

            // LW
            7'b0000011: begin
                reg_write  = 1'b1;
                mem_read   = 1'b1;
                alu_src    = 1'b1;
                mem_to_reg = 1'b1;
                alu_op     = 2'b00;
            end

            // SW
            7'b0100011: begin
                mem_write = 1'b1;
                alu_src   = 1'b1;
                alu_op    = 2'b00;
            end

            // Branch instructions
            7'b1100011: begin

                branch  = 1'b1;
                alu_src = 1'b0;
                alu_op  = 2'b01;

                case (funct3)

                    // BEQ
                    3'b000:
                        branch_type = 2'b01;

                    // BNE
                    3'b001:
                        branch_type = 2'b10;

                    default: begin
                        branch      = 1'b0;
                        branch_type = 2'b00;
                    end

                endcase
            end

            // JAL
            7'b1101111: begin
                reg_write = 1'b1;
                jump      = 1'b1;
            end

            default: begin
                reg_write   = 1'b0;
                mem_read    = 1'b0;
                mem_write   = 1'b0;
                alu_src     = 1'b0;
                mem_to_reg  = 1'b0;
                branch      = 1'b0;
                jump        = 1'b0;
                branch_type = 2'b00;
                alu_op      = 2'b00;
            end

        endcase

    end

endmodule

rtl/instruction_memory.v
module instruction_memory (
    input  wire [31:0] address,
    output reg  [31:0] instruction
);

    reg [31:0] memory [0:255];

    always @(*) begin
        instruction = memory[address[9:2]];
    end

endmodule

rtl/riscv_core.v
module riscv_core (
    input wire clk,
    input wire reset
);

    // =========================================================
    // Program Counter
    // =========================================================
    wire [31:0] pc;
    reg  [31:0] next_pc;

    // =========================================================
    // Instruction Memory
    // =========================================================
    wire [31:0] instruction;

    instruction_memory imem (
        .address(pc),
        .instruction(instruction)
    );

    // =========================================================
    // Instruction Fields
    // =========================================================
    wire [6:0] opcode = instruction[6:0];
    wire [4:0] rs1    = instruction[19:15];
    wire [4:0] rs2    = instruction[24:20];
    wire [4:0] rd     = instruction[11:7];
    wire [2:0] funct3 = instruction[14:12];
    wire [6:0] funct7 = instruction[31:25];

    // =========================================================
    // Control Unit
    // =========================================================
    wire       reg_write;
    wire       mem_read;
    wire       mem_write;
    wire       alu_src;
    wire       mem_to_reg;
    wire       branch;
    wire       jump;
    wire [1:0] branch_type;
    wire [1:0] alu_op;

    control_unit control (
        .opcode(opcode),
        .funct3(funct3),
        .reg_write(reg_write),
        .mem_read(mem_read),
        .mem_write(mem_write),
        .alu_src(alu_src),
        .mem_to_reg(mem_to_reg),
        .branch(branch),
        .jump(jump),
        .branch_type(branch_type),
        .alu_op(alu_op)
    );

    // =========================================================
    // Register File
    // =========================================================
    wire [31:0] register_data1;
    wire [31:0] register_data2;

    reg [31:0] write_back_data;

    register_file regs (
        .clk(clk),
        .reset(reset),
        .reg_write(reg_write),
        .rs1(rs1),
        .rs2(rs2),
        .rd(rd),
        .write_data(write_back_data),
        .read_data1(register_data1),
        .read_data2(register_data2)
    );

    // =========================================================
    // Immediate Generator
    // =========================================================
    wire [31:0] immediate;

    immediate_generator imm_gen (
        .instruction(instruction),
        .immediate(immediate)
    );

    // =========================================================
    // ALU Control
    // =========================================================
    reg [3:0] alu_control;

    always @(*) begin
        case (alu_op)

            // Load / Store / Address calculation
            2'b00:
                alu_control = 4'b0000;

            // Branch comparison
            2'b01:
                alu_control = 4'b0001;

            // R-type instructions
            2'b10: begin
                case ({funct7, funct3})

                    10'b0000000_000: alu_control = 4'b0000; // ADD
                    10'b0100000_000: alu_control = 4'b0001; // SUB
                    10'b0000000_111: alu_control = 4'b0010; // AND
                    10'b0000000_110: alu_control = 4'b0011; // OR
                    10'b0000000_100: alu_control = 4'b0100; // XOR
                    10'b0000000_010: alu_control = 4'b0101; // SLT

                    default: alu_control = 4'b0000;

                endcase
            end

            // I-type instructions
            2'b11: begin
                case (funct3)

                    3'b000: alu_control = 4'b0000; // ADDI
                    3'b010: alu_control = 4'b0101; // SLTI

                    default: alu_control = 4'b0000;

                endcase
            end

            default:
                alu_control = 4'b0000;

        endcase
    end

    // =========================================================
    // ALU Input Selection
    // =========================================================
    wire [31:0] alu_input_b;

    assign alu_input_b =
        alu_src ? immediate : register_data2;

    wire [31:0] alu_result;
    wire        alu_zero;

    alu alu_unit (
        .a(register_data1),
        .b(alu_input_b),
        .alu_control(alu_control),
        .result(alu_result),
        .zero(alu_zero)
    );

    // =========================================================
    // Data Memory
    // =========================================================
    wire [31:0] memory_read_data;

    data_memory dmem (
        .clk(clk),
        .reset(reset),
        .mem_read(mem_read),
        .mem_write(mem_write),
        .address(alu_result),
        .write_data(register_data2),
        .read_data(memory_read_data)
    );

    // =========================================================
    // Writeback
    // =========================================================
    always @(*) begin
        if (mem_to_reg)
            write_back_data = memory_read_data;
        else if (jump)
            write_back_data = pc + 32'd4;
        else
            write_back_data = alu_result;
    end

    // =========================================================
    // Branch Decision
    // =========================================================
    reg branch_taken;

    always @(*) begin
        branch_taken = 1'b0;

        if (branch) begin
            case (branch_type)

                // BEQ
                2'b01:
                    branch_taken = (register_data1 == register_data2);

                // BNE
                2'b10:
                    branch_taken = (register_data1 != register_data2);

                default:
                    branch_taken = 1'b0;

            endcase
        end
    end

    // =========================================================
    // Next PC Logic
    // =========================================================
    always @(*) begin

        // Default: next instruction
        next_pc = pc + 32'd4;

        // Branch
        if (branch_taken)
            next_pc = pc + immediate;

        // JAL
        if (jump)
            next_pc = pc + immediate;

    end

    // =========================================================
    // Program Counter Register
    // =========================================================
    pc pc_unit (
        .clk(clk),
        .reset(reset),
        .next_pc(next_pc),
        .pc(pc)
    );

endmodule

tb/tb_riscv_core.v
`timescale 1ns/1ps

module tb_riscv_core;

    reg clk;
    reg reset;

    // Instantiate processor
    riscv_core dut (
        .clk(clk),
        .reset(reset)
    );

    // Clock generation
    always #5 clk = ~clk;

    initial begin

    $dumpfile("waveforms/riscv_core.vcd");
    $dumpvars(0, tb_riscv_core);

        clk   = 1'b0;
        reset = 1'b1;

        // Reset processor
        #12;
        reset = 1'b0;

        // -------------------------------------------------
        // Program
        // -------------------------------------------------


// ADDI x1, x0, 10
dut.imem.memory[0] = 32'h00A00093;

// JAL x2, +8
// x2 should receive PC + 4 = 4
// Jump to instruction at PC + 8
dut.imem.memory[1] = 32'h0080016F;

// ADDI x3, x0, 99
// This instruction should be skipped
dut.imem.memory[2] = 32'h06300193;

// ADDI x4, x0, 55
// This instruction should execute
dut.imem.memory[3] = 32'h03700213;

        // Wait for execution
        #80;

        // Display register results
        $display("======================================");
        $display("RISC-V PROCESSOR TEST RESULTS");
        $display("======================================");

        $display("x1 = %0d", dut.regs.registers[1]);
        $display("x2 = %0d", dut.regs.registers[2]);
        $display("x3 = %0d", dut.regs.registers[3]);
        $display("x4 = %0d", dut.regs.registers[4]);
        $display("x5 = %0d", dut.regs.registers[5]);
        $display("x6 = %0d", dut.regs.registers[6]);
        $display("x7 = %0d", dut.regs.registers[7]);

        $display("======================================");

        $finish;

    end

endmodule

waveforms/riscv_core.vcd
$date
	Mon Sep 07 20:10:20 2026
$end
$version
	Icarus Verilog
$end
$timescale
	1ps
$end
$scope module tb_riscv_core $end
$var reg 1 ! clk $end
$var reg 1 " reset $end
$scope module dut $end
$var wire 1 ! clk $end
$var wire 1 " reset $end
$var wire 5 # rs2 [4:0] $end
$var wire 5 $ rs1 [4:0] $end
$var wire 32 % register_data2 [31:0] $end
$var wire 32 & register_data1 [31:0] $end
$var wire 1 ' reg_write $end
$var wire 5 ( rd [4:0] $end
$var wire 32 ) pc [31:0] $end
$var wire 7 * opcode [6:0] $end
$var wire 32 + memory_read_data [31:0] $end
$var wire 1 , mem_write $end
$var wire 1 - mem_to_reg $end
$var wire 1 . mem_read $end
$var wire 1 / jump $end
$var wire 32 0 instruction [31:0] $end
$var wire 32 1 immediate [31:0] $end
$var wire 7 2 funct7 [6:0] $end
$var wire 3 3 funct3 [2:0] $end
$var wire 2 4 branch_type [1:0] $end
$var wire 1 5 branch $end
$var wire 1 6 alu_zero $end
$var wire 1 7 alu_src $end
$var wire 32 8 alu_result [31:0] $end
$var wire 2 9 alu_op [1:0] $end
$var wire 32 : alu_input_b [31:0] $end
$var reg 4 ; alu_control [3:0] $end
$var reg 1 < branch_taken $end
$var reg 32 = next_pc [31:0] $end
$var reg 32 > write_back_data [31:0] $end
$scope module alu_unit $end
$var wire 4 ? alu_control [3:0] $end
$var wire 32 @ b [31:0] $end
$var wire 1 6 zero $end
$var wire 32 A a [31:0] $end
$var reg 32 B result [31:0] $end
$upscope $end
$scope module control $end
$var wire 3 C funct3 [2:0] $end
$var wire 7 D opcode [6:0] $end
$var reg 2 E alu_op [1:0] $end
$var reg 1 7 alu_src $end
$var reg 1 5 branch $end
$var reg 2 F branch_type [1:0] $end
$var reg 1 / jump $end
$var reg 1 . mem_read $end
$var reg 1 - mem_to_reg $end
$var reg 1 , mem_write $end
$var reg 1 ' reg_write $end
$upscope $end
$scope module dmem $end
$var wire 32 G address [31:0] $end
$var wire 1 ! clk $end
$var wire 1 . mem_read $end
$var wire 1 , mem_write $end
$var wire 1 " reset $end
$var wire 32 H write_data [31:0] $end
$var reg 32 I read_data [31:0] $end
$var integer 32 J i [31:0] $end
$upscope $end
$scope module imem $end
$var wire 32 K address [31:0] $end
$var reg 32 L instruction [31:0] $end
$upscope $end
$scope module imm_gen $end
$var wire 32 M instruction [31:0] $end
$var wire 7 N opcode [6:0] $end
$var reg 32 O immediate [31:0] $end
$upscope $end
$scope module pc_unit $end
$var wire 1 ! clk $end
$var wire 32 P next_pc [31:0] $end
$var wire 1 " reset $end
$var reg 32 Q pc [31:0] $end
$upscope $end
$scope module regs $end
$var wire 1 ! clk $end
$var wire 5 R rd [4:0] $end
$var wire 1 ' reg_write $end
$var wire 1 " reset $end
$var wire 5 S rs1 [4:0] $end
$var wire 5 T rs2 [4:0] $end
$var wire 32 U write_data [31:0] $end
$var wire 32 V read_data2 [31:0] $end
$var wire 32 W read_data1 [31:0] $end
$var integer 32 X i [31:0] $end
$upscope $end
$upscope $end
$upscope $end
$enddefinitions $end
$comment Show the parameter values. $end
$dumpall
$end
#0
$dumpvars
bx X
bx W
bx V
bx U
bx T
bx S
bx R
bx Q
bx P
bx O
bx N
bx M
bx L
bx K
bx J
bx I
bx H
bx G
bx F
bx E
bx D
bx C
bx B
bx A
bx @
bx ?
bx >
bx =
x<
bx ;
bx :
bx 9
bx 8
x7
x6
x5
bx 4
bx 3
bx 2
bx 1
bx 0
x/
x.
x-
x,
bx +
bx *
bx )
bx (
x'
bx &
bx %
bx $
bx #
1"
0!
$end
#5000
b0 +
b0 I
b100 =
b100 P
b0 )
b0 K
b0 Q
b100000 X
b100000000 J
1!
#10000
0!
#12000
b1010 >
b1010 U
06
b1010 8
b1010 B
b1010 G
0<
b1010 :
b1010 @
b0 ;
b0 ?
b0 %
b0 H
b0 V
b0 &
b0 A
b0 W
b11 9
b11 E
b0 4
b0 F
0/
05
0-
17
0,
0.
1'
b1010 1
b1010 O
b10011 N
b0 2
b0 3
b0 C
b1 (
b1 R
b1010 #
b1010 T
b0 $
b0 S
b10011 *
b10011 D
b101000000000000010010011 0
b101000000000000010010011 L
b101000000000000010010011 M
0"
#15000
16
b0 8
b0 B
b0 G
b1000 >
b1000 U
b0 :
b0 @
1/
b0 9
b0 E
07
1'
b1000 1
b1000 O
b1101111 N
b10 (
b10 R
b1000 #
b1000 T
b1101111 *
b1101111 D
b1100 =
b1100 P
b100000000000000101101111 0
b100000000000000101101111 L
b100000000000000101101111 M
b100 )
b100 K
b100 Q
1!
#20000
0!
#25000
06
b110111 8
b110111 B
b110111 G
b110111 :
b110111 @
b11 9
b11 E
17
0/
1'
b110111 1
b110111 O
b10011 N
b1 2
b100 (
b100 R
b10111 #
b10111 T
b10011 *
b10011 D
b110111 >
b110111 U
b10000 =
b10000 P
b11011100000000001000010011 0
b11011100000000001000010011 L
b11011100000000001000010011 M
b1100 )
b1100 K
b1100 Q
1!
#30000
0!
#35000
bx >
bx U
x6
bx 8
bx B
bx G
bx :
bx @
bx %
bx H
bx V
bx &
bx A
bx W
b0 9
b0 E
07
0'
b0 1
b0 O
bx N
bx 2
bx 3
bx C
bx (
bx R
bx #
bx T
bx $
bx S
bx *
bx D
b10100 =
b10100 P
bx 0
bx L
bx M
b10000 )
b10000 K
b10000 Q
1!
#40000
0!
#45000
b11000 =
b11000 P
b10100 )
b10100 K
b10100 Q
1!
#50000
0!
#55000
b11100 =
b11100 P
b11000 )
b11000 K
b11000 Q
1!
#60000
0!
#65000
b100000 =
b100000 P
b11100 )
b11100 K
b11100 Q
1!
#70000
0!
#75000
b100100 =
b100100 P
b100000 )
b100000 K
b100000 Q
1!
#80000
0!
#85000
b101000 =
b101000 P
b100100 )
b100100 K
b100100 Q
1!
